src/encoder.v
`default_nettype none
`timescale 1ns/1ns
module encoder #(
    parameter WIDTH = 8,
    parameter INCREMENT = 1'b1
    )(
    input clk,
    input reset,
    input a,
    input b,
    output reg [WIDTH-1:0] value
    );

    reg old_a;
    reg old_b;

    always @(posedge clk) begin 
        if(reset) begin

            old_a <= 0;
            old_b <= 0;
            value <= 0;

        end else begin

            // last values
            old_a <= a;
            old_b <= b;

            // state machine
            case ({a,old_a,b,old_b})

                4'b1000: value <= value + INCREMENT;
                4'b0111: value <= value + INCREMENT;

                4'b0010: value <= value - INCREMENT;
                4'b1101: value <= value - INCREMENT;

                default: value <= value;
            endcase
        end
    end

	`ifdef COCOTB_SIM
    initial begin
    $dumpfile ("encoder.vcd");
    $dumpvars (0, encoder);
    #1;
    end
    `endif

endmodule

encoder.vcd
$date
	Sat Jun 27 00:36:53 2026
$end
$version
	Icarus Verilog
$end
$timescale
	1ps
$end
$scope module encoder $end
$var wire 1 ! a $end
$var wire 1 " b $end
$var wire 1 # clk $end
$var wire 1 $ reset $end
$var parameter 1 % INCREMENT $end
$var parameter 32 & WIDTH $end
$var reg 1 ' old_a $end
$var reg 1 ( old_b $end
$var reg 8 ) value [7:0] $end
$upscope $end
$enddefinitions $end
$comment Show the parameter values. $end
$dumpall
b1000 &
1%
$end
#0
$dumpvars
b0 )
0(
0'
1$
1#
0"
0!
$end
#5000000
0#
#10000000
1#
#15000000
0#
#20000000
1#
#25000000
0#
#30000000
1#
#35000000
0#
#40000000
0$
1#
#45000000
0#
#50000000
1#
#55000000
0#
#60000000
1#
#65000000
0#
#70000000
1#
#75000000
0#
#80000000
1#
#85000000
0#
#90000000
1#
#95000000
0#
#100000000
1#
#105000000
0#
#110000000
1#
#115000000
0#
#120000000
1#
#125000000
0#
#130000000
1#
#135000000
0#
#140000000
1!
1#
#145000000
0#
#150000000
b1 )
1'
1#
#155000000
0#
#160000000
1#
#165000000
0#
#170000000
1#
#175000000
0#
#180000000
1#
#185000000
0#
#190000000
1"
1#
#195000000
0#
#200000000
1(
1#
#205000000
0#
#210000000
1#
#215000000
0#
#220000000
1#
#225000000
0#
#230000000
1#
#235000000
0#
#240000000
0!
1#
#245000000
0#
#250000000
b10 )
0'
1#
#255000000
0#
#260000000
1#
#265000000
0#
#270000000
1#
#275000000
0#
#280000000
1#
#285000000
0#
#290000000
0"
1#
#295000000
0#
#300000000
0(
1#
#305000000
0#
#310000000
1#
#315000000
0#
#320000000
1#
#325000000
0#
#330000000
1#
#335000000
0#
#340000000
1!
1#
#345000000
0#
#350000000
b11 )
1'
1#
#355000000
0#
#360000000
1#
#365000000
0#
#370000000
1#
#375000000
0#
#380000000
1#
#385000000
0#
#390000000
1"
1#
#395000000
0#
#400000000
1(
1#
#405000000
0#
#410000000
1#
#415000000
0#
#420000000
1#
#425000000
0#
#430000000
1#
#435000000
0#
#440000000
0!
1#
#445000000
0#
#450000000
b100 )
0'
1#
#455000000
0#
#460000000
1#
#465000000
0#
#470000000
1#
#475000000
0#
#480000000
1#
#485000000
0#
#490000000
0"
1#
#495000000
0#
#500000000
0(
1#
#505000000
0#
#510000000
1#
#515000000
0#
#520000000
1#
#525000000
0#
#530000000
1#
#535000000
0#
#540000000
1!
1#
#545000000
0#
#550000000
b101 )
1'
1#
#555000000
0#
#560000000
1#
#565000000
0#
#570000000
1#
#575000000
0#
#580000000
1#
#585000000
0#
#590000000
1"
1#
#595000000
0#
#600000000
1(
1#
#605000000
0#
#610000000
1#
#615000000
0#
#620000000
1#
#625000000
0#
#630000000
1#
#635000000
0#
#640000000
0!
1#
#645000000
0#
#650000000
b110 )
0'
1#
#655000000
0#
#660000000
1#
#665000000
0#
#670000000
1#
#675000000
0#
#680000000
1#
#685000000
0#
#690000000
0"
1#
#695000000
0#
#700000000
0(
1#
#705000000
0#
#710000000
1#
#715000000
0#
#720000000
1#
#725000000
0#
#730000000
1#
#735000000
0#
#740000000
1!
1#
#745000000
0#
#750000000
b111 )
1'
1#
#755000000
0#
#760000000
1#
#765000000
0#
#770000000
1#
#775000000
0#
#780000000
1#
#785000000
0#
#790000000
1"
1#
#795000000
0#
#800000000
1(
1#
#805000000
0#
#810000000
1#
#815000000
0#
#820000000
1#
#825000000
0#
#830000000
1#
#835000000
0#
#840000000
0!
1#
#845000000
0#
#850000000
b1000 )
0'
1#
#855000000
0#
#860000000
1#
#865000000
0#
#870000000
1#
#875000000
0#
#880000000
1#
#885000000
0#
#890000000
0"
1#
#895000000
0#
#900000000
0(
1#
#905000000
0#
#910000000
1#
#915000000
0#
#920000000
1#
#925000000
0#
#930000000
1#
#935000000
0#
#940000000
1!
1#
#945000000
0#
#950000000
b1001 )
1'
1#
#955000000
0#
#960000000
1#
#965000000
0#
#970000000
1#
#975000000
0#
#980000000
1#
#985000000
0#
#990000000
1"
1#
#995000000
0#
#1000000000
1(
1#
#1005000000
0#
#1010000000
1#
#1015000000
0#
#1020000000
1#
#1025000000
0#
#1030000000
1#
#1035000000
0#
#1040000000
0!
1#
#1045000000
0#
#1050000000
b1010 )
0'
1#
#1055000000
0#
#1060000000
1#
#1065000000
0#
#1070000000
1#
#1075000000
0#
#1080000000
1#
#1085000000
0#
#1090000000
0"
1#
#1095000000
0#
#1100000000
0(
1#
#1105000000
0#
#1110000000
1#
#1115000000
0#
#1120000000
1#
#1125000000
0#
#1130000000
1#
#1135000000
0#
#1140000000
1!
1#
#1145000000
0#
#1150000000
b1011 )
1'
1#
#1155000000
0#
#1160000000
1#
#1165000000
0#
#1170000000
1#
#1175000000
0#
#1180000000
1#
#1185000000
0#
#1190000000
1"
1#
#1195000000
0#
#1200000000
1(
1#
#1205000000
0#
#1210000000
1#
#1215000000
0#
#1220000000
1#
#1225000000
0#
#1230000000
1#
#1235000000
0#
#1240000000
0!
1#
#1245000000
0#
#1250000000
b1100 )
0'
1#
#1255000000
0#
#1260000000
1#
#1265000000
0#
#1270000000
1#
#1275000000
0#
#1280000000
1#
#1285000000
0#
#1290000000
0"
1#
#1295000000
0#
#1300000000
0(
1#
#1305000000
0#
#1310000000
1#
#1315000000
0#
#1320000000
1#
#1325000000
0#
#1330000000
1#
#1335000000
0#
#1340000000
1!
1#
#1345000000
0#
#1350000000
b1101 )
1'
1#
#1355000000
0#
#1360000000
1#
#1365000000
0#
#1370000000
1#
#1375000000
0#
#1380000000
1#
#1385000000
0#
#1390000000
1"
1#
#1395000000
0#
#1400000000
1(
1#
#1405000000
0#
#1410000000
1#
#1415000000
0#
#1420000000
1#
#1425000000
0#
#1430000000
1#
#1435000000
0#
#1440000000
0!
1#
#1445000000
0#
#1450000000
b1110 )
0'
1#
#1455000000
0#
#1460000000
1#
#1465000000
0#
#1470000000
1#
#1475000000
0#
#1480000000
1#
#1485000000
0#
#1490000000
0"
1#
#1495000000
0#
#1500000000
0(
1#
#1505000000
0#
#1510000000
1#
#1515000000
0#
#1520000000
1#
#1525000000
0#
#1530000000
1#
#1535000000
0#
#1540000000
1!
1#
#1545000000
0#
#1550000000
b1111 )
1'
1#
#1555000000
0#
#1560000000
1#
#1565000000
0#
#1570000000
1#
#1575000000
0#
#1580000000
1#
#1585000000
0#
#1590000000
1"
1#
#1595000000
0#
#1600000000
1(
1#
#1605000000
0#
#1610000000
1#
#1615000000
0#
#1620000000
1#
#1625000000
0#
#1630000000
1#
#1635000000
0#
#1640000000
0!
1#
#1645000000
0#
#1650000000
b10000 )
0'
1#
#1655000000
0#
#1660000000
1#
#1665000000
0#
#1670000000
1#
#1675000000
0#
#1680000000
1#
#1685000000
0#
#1690000000
0"
1#
#1695000000
0#
#1700000000
0(
1#
#1705000000
0#
#1710000000
1#
#1715000000
0#
#1720000000
1#
#1725000000
0#
#1730000000
1#
#1735000000
0#
#1740000000
1!
1#
#1745000000
0#
#1750000000
b10001 )
1'
1#
#1755000000
0#
#1760000000
1#
#1765000000
0#
#1770000000
1#
#1775000000
0#
#1780000000
1#
#1785000000
0#
#1790000000
1"
1#
#1795000000
0#
#1800000000
1(
1#
#1805000000
0#
#1810000000
1#
#1815000000
0#
#1820000000
1#
#1825000000
0#
#1830000000
1#
#1835000000
0#
#1840000000
0!
1#
#1845000000
0#
#1850000000
b10010 )
0'
1#
#1855000000
0#
#1860000000
1#
#1865000000
0#
#1870000000
1#
#1875000000
0#
#1880000000
1#
#1885000000
0#
#1890000000
0"
1#
#1895000000
0#
#1900000000
0(
1#
#1905000000
0#
#1910000000
1#
#1915000000
0#
#1920000000
1#
#1925000000
0#
#1930000000
1#
#1935000000
0#
#1940000000
1!
1#
#1945000000
0#
#1950000000
b10011 )
1'
1#
#1955000000
0#
#1960000000
1#
#1965000000
0#
#1970000000
1#
#1975000000
0#
#1980000000
1#
#1985000000
0#
#1990000000
1"
1#
#1995000000
0#
#2000000000
1(
1#
#2005000000
0#
#2010000000
1#
#2015000000
0#
#2020000000
1#
#2025000000
0#
#2030000000
1#
#2035000000
0#
#2040000000
0!
1#
#2045000000
0#
#2050000000
b10100 )
0'
1#
#2055000000
0#
#2060000000
1#
#2065000000
0#
#2070000000
1#
#2075000000
0#
#2080000000
1#
#2085000000
0#
#2090000000
0"
1#
#2095000000
0#
#2100000000
0(
1#
#2105000000
0#
#2110000000
1#
#2115000000
0#
#2120000000
1#
#2125000000
0#
#2130000000
1#
#2135000000
0#
#2140000000
1!
1#
#2145000000
0#
#2150000000
b10101 )
1'
1#
#2155000000
0#
#2160000000
1#
#2165000000
0#
#2170000000
1#
#2175000000
0#
#2180000000
1#
#2185000000
0#
#2190000000
1"
1#
#2195000000
0#
#2200000000
1(
1#
#2205000000
0#
#2210000000
1#
#2215000000
0#
#2220000000
1#
#2225000000
0#
#2230000000
1#
#2235000000
0#
#2240000000
0!
1#
#2245000000
0#
#2250000000
b10110 )
0'
1#
#2255000000
0#
#2260000000
1#
#2265000000
0#
#2270000000
1#
#2275000000
0#
#2280000000
1#
#2285000000
0#
#2290000000
0"
1#
#2295000000
0#
#2300000000
0(
1#
#2305000000
0#
#2310000000
1#
#2315000000
0#
#2320000000
1#
#2325000000
0#
#2330000000
1#
#2335000000
0#
#2340000000
1!
1#
#2345000000
0#
#2350000000
b10111 )
1'
1#
#2355000000
0#
#2360000000
1#
#2365000000
0#
#2370000000
1#
#2375000000
0#
#2380000000
1#
#2385000000
0#
#2390000000
1"
1#
#2395000000
0#
#2400000000
1(
1#
#2405000000
0#
#2410000000
1#
#2415000000
0#
#2420000000
1#
#2425000000
0#
#2430000000
1#
#2435000000
0#
#2440000000
0!
1#
#2445000000
0#
#2450000000
b11000 )
0'
1#
#2455000000
0#
#2460000000
1#
#2465000000
0#
#2470000000
1#
#2475000000
0#
#2480000000
1#
#2485000000
0#
#2490000000
0"
1#
#2495000000
0#
#2500000000
0(
1#
#2505000000
0#
#2510000000
1#
#2515000000
0#
#2520000000
1#
#2525000000
0#
#2530000000
1#
#2535000000
0#
#2540000000
1!
1#
#2545000000
0#
#2550000000
b11001 )
1'
1#
#2555000000
0#
#2560000000
1#
#2565000000
0#
#2570000000
1#
#2575000000
0#
#2580000000
1#
#2585000000
0#
#2590000000
1"
1#
#2595000000
0#
#2600000000
1(
1#
#2605000000
0#
#2610000000
1#
#2615000000
0#
#2620000000
1#
#2625000000
0#
#2630000000
1#
#2635000000
0#
#2640000000
0!
1#
#2645000000
0#
#2650000000
b11010 )
0'
1#
#2655000000
0#
#2660000000
1#
#2665000000
0#
#2670000000
1#
#2675000000
0#
#2680000000
1#
#2685000000
0#
#2690000000
0"
1#
#2695000000
0#
#2700000000
0(
1#
#2705000000
0#
#2710000000
1#
#2715000000
0#
#2720000000
1#
#2725000000
0#
#2730000000
1#
#2735000000
0#
#2740000000
1!
1#
#2745000000
0#
#2750000000
b11011 )
1'
1#
#2755000000
0#
#2760000000
1#
#2765000000
0#
#2770000000
1#
#2775000000
0#
#2780000000
1#
#2785000000
0#
#2790000000
1"
1#
#2795000000
0#
#2800000000
1(
1#
#2805000000
0#
#2810000000
1#
#2815000000
0#
#2820000000
1#
#2825000000
0#
#2830000000
1#
#2835000000
0#
#2840000000
0!
1#
#2845000000
0#
#2850000000
b11100 )
0'
1#
#2855000000
0#
#2860000000
1#
#2865000000
0#
#2870000000
1#
#2875000000
0#
#2880000000
1#
#2885000000
0#
#2890000000
0"
1#
#2895000000
0#
#2900000000
0(
1#
#2905000000
0#
#2910000000
1#
#2915000000
0#
#2920000000
1#
#2925000000
0#
#2930000000
1#
#2935000000
0#
#2940000000
1!
1#
#2945000000
0#
#2950000000
b11101 )
1'
1#
#2955000000
0#
#2960000000
1#
#2965000000
0#
#2970000000
1#
#2975000000
0#
#2980000000
1#
#2985000000
0#
#2990000000
1"
1#
#2995000000
0#
#3000000000
1(
1#
#3005000000
0#
#3010000000
1#
#3015000000
0#
#3020000000
1#
#3025000000
0#
#3030000000
1#
#3035000000
0#
#3040000000
0!
1#
#3045000000
0#
#3050000000
b11110 )
0'
1#
#3055000000
0#
#3060000000
1#
#3065000000
0#
#3070000000
1#
#3075000000
0#
#3080000000
1#
#3085000000
0#
#3090000000
0"
1#
#3095000000
0#
#3100000000
0(
1#
#3105000000
0#
#3110000000
1#
#3115000000
0#
#3120000000
1#
#3125000000
0#
#3130000000
1#
#3135000000
0#
#3140000000
1!
1#
#3145000000
0#
#3150000000
b11111 )
1'
1#
#3155000000
0#
#3160000000
1#
#3165000000
0#
#3170000000
1#
#3175000000
0#
#3180000000
1#
#3185000000
0#
#3190000000
1"
1#
#3195000000
0#
#3200000000
1(
1#
#3205000000
0#
#3210000000
1#
#3215000000
0#
#3220000000
1#
#3225000000
0#
#3230000000
1#
#3235000000
0#
#3240000000
0!
1#
#3245000000
0#
#3250000000
b100000 )
0'
1#
#3255000000
0#
#3260000000
1#
#3265000000
0#
#3270000000
1#
#3275000000
0#
#3280000000
1#
#3285000000
0#
#3290000000
0"
1#
#3295000000
0#
#3300000000
0(
1#
#3305000000
0#
#3310000000
1#
#3315000000
0#
#3320000000
1#
#3325000000
0#
#3330000000
1#
#3335000000
0#
#3340000000
1!
1#
#3345000000
0#
#3350000000
b100001 )
1'
1#
#3355000000
0#
#3360000000
1#
#3365000000
0#
#3370000000
1#
#3375000000
0#
#3380000000
1#
#3385000000
0#
#3390000000
1"
1#
#3395000000
0#
#3400000000
1(
1#
#3405000000
0#
#3410000000
1#
#3415000000
0#
#3420000000
1#
#3425000000
0#
#3430000000
1#
#3435000000
0#
#3440000000
0!
1#
#3445000000
0#
#3450000000
b100010 )
0'
1#
#3455000000
0#
#3460000000
1#
#3465000000
0#
#3470000000
1#
#3475000000
0#
#3480000000
1#
#3485000000
0#
#3490000000
0"
1#
#3495000000
0#
#3500000000
0(
1#
#3505000000
0#
#3510000000
1#
#3515000000
0#
#3520000000
1#
#3525000000
0#
#3530000000
1#
#3535000000
0#
#3540000000
1!
1#
#3545000000
0#
#3550000000
b100011 )
1'
1#
#3555000000
0#
#3560000000
1#
#3565000000
0#
#3570000000
1#
#3575000000
0#
#3580000000
1#
#3585000000
0#
#3590000000
1"
1#
#3595000000
0#
#3600000000
1(
1#
#3605000000
0#
#3610000000
1#
#3615000000
0#
#3620000000
1#
#3625000000
0#
#3630000000
1#
#3635000000
0#
#3640000000
0!
1#
#3645000000
0#
#3650000000
b100100 )
0'
1#
#3655000000
0#
#3660000000
1#
#3665000000
0#
#3670000000
1#
#3675000000
0#
#3680000000
1#
#3685000000
0#
#3690000000
0"
1#
#3695000000
0#
#3700000000
0(
1#
#3705000000
0#
#3710000000
1#
#3715000000
0#
#3720000000
1#
#3725000000
0#
#3730000000
1#
#3735000000
0#
#3740000000
1!
1#
#3745000000
0#
#3750000000
b100101 )
1'
1#
#3755000000
0#
#3760000000
1#
#3765000000
0#
#3770000000
1#
#3775000000
0#
#3780000000
1#
#3785000000
0#
#3790000000
1"
1#
#3795000000
0#
#3800000000
1(
1#
#3805000000
0#
#3810000000
1#
#3815000000
0#
#3820000000
1#
#3825000000
0#
#3830000000
1#
#3835000000
0#
#3840000000
0!
1#
#3845000000
0#
#3850000000
b100110 )
0'
1#
#3855000000
0#
#3860000000
1#
#3865000000
0#
#3870000000
1#
#3875000000
0#
#3880000000
1#
#3885000000
0#
#3890000000
0"
1#
#3895000000
0#
#3900000000
0(
1#
#3905000000
0#
#3910000000
1#
#3915000000
0#
#3920000000
1#
#3925000000
0#
#3930000000
1#
#3935000000
0#
#3940000000
1!
1#
#3945000000
0#
#3950000000
b100111 )
1'
1#
#3955000000
0#
#3960000000
1#
#3965000000
0#
#3970000000
1#
#3975000000
0#
#3980000000
1#
#3985000000
0#
#3990000000
1"
1#
#3995000000
0#
#4000000000
1(
1#
#4005000000
0#
#4010000000
1#
#4015000000
0#
#4020000000
1#
#4025000000
0#
#4030000000
1#
#4035000000
0#
#4040000000
0!
1#
#4045000000
0#
#4050000000
b101000 )
0'
1#
#4055000000
0#
#4060000000
1#
#4065000000
0#
#4070000000
1#
#4075000000
0#
#4080000000
1#
#4085000000
0#
#4090000000
0"
1#
#4095000000
0#
#4100000000
0(
1#
#4105000000
0#
#4110000000
1#
#4115000000
0#
#4120000000
1#
#4125000000
0#
#4130000000
1#
#4135000000
0#
#4140000000
1!
1#
#4145000000
0#
#4150000000
b101001 )
1'
1#
#4155000000
0#
#4160000000
1#
#4165000000
0#
#4170000000
1#
#4175000000
0#
#4180000000
1#
#4185000000
0#
#4190000000
1"
1#
#4195000000
0#
#4200000000
1(
1#
#4205000000
0#
#4210000000
1#
#4215000000
0#
#4220000000
1#
#4225000000
0#
#4230000000
1#
#4235000000
0#
#4240000000
0!
1#
#4245000000
0#
#4250000000
b101010 )
0'
1#
#4255000000
0#
#4260000000
1#
#4265000000
0#
#4270000000
1#
#4275000000
0#
#4280000000
1#
#4285000000
0#
#4290000000
0"
1#
#4295000000
0#
#4300000000
0(
1#
#4305000000
0#
#4310000000
1#
#4315000000
0#
#4320000000
1#
#4325000000
0#
#4330000000
1#
#4335000000
0#
#4340000000
1!
1#
#4345000000
0#
#4350000000
b101011 )
1'
1#
#4355000000
0#
#4360000000
1#
#4365000000
0#
#4370000000
1#
#4375000000
0#
#4380000000
1#
#4385000000
0#
#4390000000
1"
1#
#4395000000
0#
#4400000000
1(
1#
#4405000000
0#
#4410000000
1#
#4415000000
0#
#4420000000
1#
#4425000000
0#
#4430000000
1#
#4435000000
0#
#4440000000
0!
1#
#4445000000
0#
#4450000000
b101100 )
0'
1#
#4455000000
0#
#4460000000
1#
#4465000000
0#
#4470000000
1#
#4475000000
0#
#4480000000
1#
#4485000000
0#
#4490000000
0"
1#
#4495000000
0#
#4500000000
0(
1#
#4505000000
0#
#4510000000
1#
#4515000000
0#
#4520000000
1#
#4525000000
0#
#4530000000
1#
#4535000000
0#
#4540000000
1!
1#
#4545000000
0#
#4550000000
b101101 )
1'
1#
#4555000000
0#
#4560000000
1#
#4565000000
0#
#4570000000
1#
#4575000000
0#
#4580000000
1#
#4585000000
0#
#4590000000
1"
1#
#4595000000
0#
#4600000000
1(
1#
#4605000000
0#
#4610000000
1#
#4615000000
0#
#4620000000
1#
#4625000000
0#
#4630000000
1#
#4635000000
0#
#4640000000
0!
1#
#4645000000
0#
#4650000000
b101110 )
0'
1#
#4655000000
0#
#4660000000
1#
#4665000000
0#
#4670000000
1#
#4675000000
0#
#4680000000
1#
#4685000000
0#
#4690000000
0"
1#
#4695000000
0#
#4700000000
0(
1#
#4705000000
0#
#4710000000
1#
#4715000000
0#
#4720000000
1#
#4725000000
0#
#4730000000
1#
#4735000000
0#
#4740000000
1!
1#
#4745000000
0#
#4750000000
b101111 )
1'
1#
#4755000000
0#
#4760000000
1#
#4765000000
0#
#4770000000
1#
#4775000000
0#
#4780000000
1#
#4785000000
0#
#4790000000
1"
1#
#4795000000
0#
#4800000000
1(
1#
#4805000000
0#
#4810000000
1#
#4815000000
0#
#4820000000
1#
#4825000000
0#
#4830000000
1#
#4835000000
0#
#4840000000
0!
1#
#4845000000
0#
#4850000000
b110000 )
0'
1#
#4855000000
0#
#4860000000
1#
#4865000000
0#
#4870000000
1#
#4875000000
0#
#4880000000
1#
#4885000000
0#
#4890000000
0"
1#
#4895000000
0#
#4900000000
0(
1#
#4905000000
0#
#4910000000
1#
#4915000000
0#
#4920000000
1#
#4925000000
0#
#4930000000
1#
#4935000000
0#
#4940000000
1!
1#
#4945000000
0#
#4950000000
b110001 )
1'
1#
#4955000000
0#
#4960000000
1#
#4965000000
0#
#4970000000
1#
#4975000000
0#
#4980000000
1#
#4985000000
0#
#4990000000
1"
1#
#4995000000
0#
#5000000000
1(
1#
#5005000000
0#
#5010000000
1#
#5015000000
0#
#5020000000
1#
#5025000000
0#
#5030000000
1#
#5035000000
0#
#5040000000
0!
1#
#5045000000
0#
#5050000000
b110010 )
0'
1#
#5055000000
0#
#5060000000
1#
#5065000000
0#
#5070000000
1#
#5075000000
0#
#5080000000
1#
#5085000000
0#
#5090000000
0"
1#
#5095000000
0#
#5100000000
0(
1#
#5105000000
0#
#5110000000
1#
#5115000000
0#
#5120000000
1#
#5125000000
0#
#5130000000
1#
#5135000000
0#
#5140000000
1!
1#
#5145000000
0#
#5150000000
b110011 )
1'
1#
#5155000000
0#
#5160000000
1#
#5165000000
0#
#5170000000
1#
#5175000000
0#
#5180000000
1#
#5185000000
0#
#5190000000
1"
1#
#5195000000
0#
#5200000000
1(
1#
#5205000000
0#
#5210000000
1#
#5215000000
0#
#5220000000
1#
#5225000000
0#
#5230000000
1#
#5235000000
0#
#5240000000
0!
1#
#5245000000
0#
#5250000000
b110100 )
0'
1#
#5255000000
0#
#5260000000
1#
#5265000000
0#
#5270000000
1#
#5275000000
0#
#5280000000
1#
#5285000000
0#
#5290000000
0"
1#
#5295000000
0#
#5300000000
0(
1#
#5305000000
0#
#5310000000
1#
#5315000000
0#
#5320000000
1#
#5325000000
0#
#5330000000
1#
#5335000000
0#
#5340000000
1!
1#
#5345000000
0#
#5350000000
b110101 )
1'
1#
#5355000000
0#
#5360000000
1#
#5365000000
0#
#5370000000
1#
#5375000000
0#
#5380000000
1#
#5385000000
0#
#5390000000
1"
1#
#5395000000
0#
#5400000000
1(
1#
#5405000000
0#
#5410000000
1#
#5415000000
0#
#5420000000
1#
#5425000000
0#
#5430000000
1#
#5435000000
0#
#5440000000
0!
1#
#5445000000
0#
#5450000000
b110110 )
0'
1#
#5455000000
0#
#5460000000
1#
#5465000000
0#
#5470000000
1#
#5475000000
0#
#5480000000
1#
#5485000000
0#
#5490000000
0"
1#
#5495000000
0#
#5500000000
0(
1#
#5505000000
0#
#5510000000
1#
#5515000000
0#
#5520000000
1#
#5525000000
0#
#5530000000
1#
#5535000000
0#
#5540000000
1!
1#
#5545000000
0#
#5550000000
b110111 )
1'
1#
#5555000000
0#
#5560000000
1#
#5565000000
0#
#5570000000
1#
#5575000000
0#
#5580000000
1#
#5585000000
0#
#5590000000
1"
1#
#5595000000
0#
#5600000000
1(
1#
#5605000000
0#
#5610000000
1#
#5615000000
0#
#5620000000
1#
#5625000000
0#
#5630000000
1#
#5635000000
0#
#5640000000
0!
1#
#5645000000
0#
#5650000000
b111000 )
0'
1#
#5655000000
0#
#5660000000
1#
#5665000000
0#
#5670000000
1#
#5675000000
0#
#5680000000
1#
#5685000000
0#
#5690000000
0"
1#
#5695000000
0#
#5700000000
0(
1#
#5705000000
0#
#5710000000
1#
#5715000000
0#
#5720000000
1#
#5725000000
0#
#5730000000
1#
#5735000000
0#
#5740000000
1!
1#
#5745000000
0#
#5750000000
b111001 )
1'
1#
#5755000000
0#
#5760000000
1#
#5765000000
0#
#5770000000
1#
#5775000000
0#
#5780000000
1#
#5785000000
0#
#5790000000
1"
1#
#5795000000
0#
#5800000000
1(
1#
#5805000000
0#
#5810000000
1#
#5815000000
0#
#5820000000
1#
#5825000000
0#
#5830000000
1#
#5835000000
0#
#5840000000
0!
1#
#5845000000
0#
#5850000000
b111010 )
0'
1#
#5855000000
0#
#5860000000
1#
#5865000000
0#
#5870000000
1#
#5875000000
0#
#5880000000
1#
#5885000000
0#
#5890000000
0"
1#
#5895000000
0#
#5900000000
0(
1#
#5905000000
0#
#5910000000
1#
#5915000000
0#
#5920000000
1#
#5925000000
0#
#5930000000
1#
#5935000000
0#
#5940000000
1!
1#
#5945000000
0#
#5950000000
b111011 )
1'
1#
#5955000000
0#
#5960000000
1#
#5965000000
0#
#5970000000
1#
#5975000000
0#
#5980000000
1#
#5985000000
0#
#5990000000
1"
1#
#5995000000
0#
#6000000000
1(
1#
#6005000000
0#
#6010000000
1#
#6015000000
0#
#6020000000
1#
#6025000000
0#
#6030000000
1#
#6035000000
0#
#6040000000
0!
1#
#6045000000
0#
#6050000000
b111100 )
0'
1#
#6055000000
0#
#6060000000
1#
#6065000000
0#
#6070000000
1#
#6075000000
0#
#6080000000
1#
#6085000000
0#
#6090000000
0"
1#
#6095000000
0#
#6100000000
0(
1#
#6105000000
0#
#6110000000
1#
#6115000000
0#
#6120000000
1#
#6125000000
0#
#6130000000
1#
#6135000000
0#
#6140000000
1!
1#
#6145000000
0#
#6150000000
b111101 )
1'
1#
#6155000000
0#
#6160000000
1#
#6165000000
0#
#6170000000
1#
#6175000000
0#
#6180000000
1#
#6185000000
0#
#6190000000
1"
1#
#6195000000
0#
#6200000000
1(
1#
#6205000000
0#
#6210000000
1#
#6215000000
0#
#6220000000
1#
#6225000000
0#
#6230000000
1#
#6235000000
0#
#6240000000
0!
1#
#6245000000
0#
#6250000000
b111110 )
0'
1#
#6255000000
0#
#6260000000
1#
#6265000000
0#
#6270000000
1#
#6275000000
0#
#6280000000
1#
#6285000000
0#
#6290000000
0"
1#
#6295000000
0#
#6300000000
0(
1#
#6305000000
0#
#6310000000
1#
#6315000000
0#
#6320000000
1#
#6325000000
0#
#6330000000
1#
#6335000000
0#
#6340000000
1!
1#
#6345000000
0#
#6350000000
b111111 )
1'
1#
#6355000000
0#
#6360000000
1#
#6365000000
0#
#6370000000
1#
#6375000000
0#
#6380000000
1#
#6385000000
0#
#6390000000
1"
1#
#6395000000
0#
#6400000000
1(
1#
#6405000000
0#
#6410000000
1#
#6415000000
0#
#6420000000
1#
#6425000000
0#
#6430000000
1#
#6435000000
0#
#6440000000
0!
1#
#6445000000
0#
#6450000000
b1000000 )
0'
1#
#6455000000
0#
#6460000000
1#
#6465000000
0#
#6470000000
1#
#6475000000
0#
#6480000000
1#
#6485000000
0#
#6490000000
0"
1#
#6495000000
0#
#6500000000
0(
1#
#6505000000
0#
#6510000000
1#
#6515000000
0#
#6520000000
1#
#6525000000
0#
#6530000000
1#
#6535000000
0#
#6540000000
1!
1#
#6545000000
0#
#6550000000
b1000001 )
1'
1#
#6555000000
0#
#6560000000
1#
#6565000000
0#
#6570000000
1#
#6575000000
0#
#6580000000
1#
#6585000000
0#
#6590000000
1"
1#
#6595000000
0#
#6600000000
1(
1#
#6605000000
0#
#6610000000
1#
#6615000000
0#
#6620000000
1#
#6625000000
0#
#6630000000
1#
#6635000000
0#
#6640000000
0!
1#
#6645000000
0#
#6650000000
b1000010 )
0'
1#
#6655000000
0#
#6660000000
1#
#6665000000
0#
#6670000000
1#
#6675000000
0#
#6680000000
1#
#6685000000
0#
#6690000000
0"
1#
#6695000000
0#
#6700000000
0(
1#
#6705000000
0#
#6710000000
1#
#6715000000
0#
#6720000000
1#
#6725000000
0#
#6730000000
1#
#6735000000
0#
#6740000000
1!
1#
#6745000000
0#
#6750000000
b1000011 )
1'
1#
#6755000000
0#
#6760000000
1#
#6765000000
0#
#6770000000
1#
#6775000000
0#
#6780000000
1#
#6785000000
0#
#6790000000
1"
1#
#6795000000
0#
#6800000000
1(
1#
#6805000000
0#
#6810000000
1#
#6815000000
0#
#6820000000
1#
#6825000000
0#
#6830000000
1#
#6835000000
0#
#6840000000
0!
1#
#6845000000
0#
#6850000000
b1000100 )
0'
1#
#6855000000
0#
#6860000000
1#
#6865000000
0#
#6870000000
1#
#6875000000
0#
#6880000000
1#
#6885000000
0#
#6890000000
0"
1#
#6895000000
0#
#6900000000
0(
1#
#6905000000
0#
#6910000000
1#
#6915000000
0#
#6920000000
1#
#6925000000
0#
#6930000000
1#
#6935000000
0#
#6940000000
1!
1#
#6945000000
0#
#6950000000
b1000101 )
1'
1#
#6955000000
0#
#6960000000
1#
#6965000000
0#
#6970000000
1#
#6975000000
0#
#6980000000
1#
#6985000000
0#
#6990000000
1"
1#
#6995000000
0#
#7000000000
1(
1#
#7005000000
0#
#7010000000
1#
#7015000000
0#
#7020000000
1#
#7025000000
0#
#7030000000
1#
#7035000000
0#
#7040000000
0!
1#
#7045000000
0#
#7050000000
b1000110 )
0'
1#
#7055000000
0#
#7060000000
1#
#7065000000
0#
#7070000000
1#
#7075000000
0#
#7080000000
1#
#7085000000
0#
#7090000000
0"
1#
#7095000000
0#
#7100000000
0(
1#
#7105000000
0#
#7110000000
1#
#7115000000
0#
#7120000000
1#
#7125000000
0#
#7130000000
1#
#7135000000
0#
#7140000000
1!
1#
#7145000000
0#
#7150000000
b1000111 )
1'
1#
#7155000000
0#
#7160000000
1#
#7165000000
0#
#7170000000
1#
#7175000000
0#
#7180000000
1#
#7185000000
0#
#7190000000
1"
1#
#7195000000
0#
#7200000000
1(
1#
#7205000000
0#
#7210000000
1#
#7215000000
0#
#7220000000
1#
#7225000000
0#
#7230000000
1#
#7235000000
0#
#7240000000
0!
1#
#7245000000
0#
#7250000000
b1001000 )
0'
1#
#7255000000
0#
#7260000000
1#
#7265000000
0#
#7270000000
1#
#7275000000
0#
#7280000000
1#
#7285000000
0#
#7290000000
0"
1#
#7295000000
0#
#7300000000
0(
1#
#7305000000
0#
#7310000000
1#
#7315000000
0#
#7320000000
1#
#7325000000
0#
#7330000000
1#
